[
  {
    "title": "Columbia Seligman Global Technology Fund Maintained its Position in Apple ( AAPL )",
    "domain": "insidermonkey.com",
    "seendate": "20250313",
    "url": "https://www.insidermonkey.com/blog/columbia-seligman-global-technology-fund-maintained-its-position-in-apple-inc-aapl-1480880/"
  },
  {
    "title": "Apple Stock : Why It Now A Screaming Buy ( NASDAQ : AAPL )",
    "domain": "seekingalpha.com",
    "seendate": "20250313",
    "url": "https://seekingalpha.com/article/4767320-apple-stock-why-its-now-a-screaming-buy"
  },
  {
    "title": "Morgan Stanley Cuts the Price Target on Apple Stock",
    "domain": "biztoc.com",
    "seendate": "20250313",
    "url": "https://biztoc.com/x/4af617ab6cb21fe9"
  },
  {
    "title": "Baystreet . ca - Why Apple is a Boring Brand , Strong Buy Stock",
    "domain": "baystreet.ca",
    "seendate": "20250313",
    "url": "http://baystreet.ca/articles/stockstowatch/109408/Why-Apple-is-a-Boring-Brand-Strong-Buy-Stock"
  },
  {
    "title": "Nasdaq Correction : Id Consider Buying the Dip on All  Magnificent Seven  Stocks -- Except This One",
    "domain": "finance.yahoo.com",
    "seendate": "20250313",
    "url": "https://finance.yahoo.com/news/nasdaq-correction-id-consider-buying-163200397.html"
  },
  {
    "title": "Apple is having a really bad week . Here why",
    "domain": "cnbc.com",
    "seendate": "20250313",
    "url": "https://www.cnbc.com/2025/03/13/apple-is-having-a-really-bad-week-heres-why.html"
  },
  {
    "title": "Nasdaq Correction : Id Consider Buying the Dip on All  Magnificent Seven  Stocks -- Except This One",
    "domain": "fool.com",
    "seendate": "20250313",
    "url": "https://www.fool.com/investing/2025/03/12/nasdaq-correction-id-consider-buying-the-dip-on-al/"
  },
  {
    "title": "Top Retail Stocks To Watch Today \u2013 March 13th",
    "domain": "theenterpriseleader.com",
    "seendate": "20250313",
    "url": "https://theenterpriseleader.com/2025/03/13/top-retail-stocks-to-watch-today-march-13th.html"
  },
  {
    "title": "Best Technology Stocks To Follow Now \u2013 March 13th",
    "domain": "tickerreport.com",
    "seendate": "20250313",
    "url": "https://www.tickerreport.com/banking-finance/12873482/best-technology-stocks-to-follow-now-march-13th.html"
  },
  {
    "title": "Best Technology Stocks To Follow Now \u2013 March 13th",
    "domain": "dailypolitical.com",
    "seendate": "20250313",
    "url": "https://www.dailypolitical.com/2025/03/13/best-technology-stocks-to-follow-now-march-13th.html"
  },
  {
    "title": "Wall Street Lunch : Inflation Eases But Warning Signs Lurk",
    "domain": "seekingalpha.com",
    "seendate": "20250313",
    "url": "https://seekingalpha.com/article/4766884-wall-street-lunch-inflations-gentle-slowdown-gives-breathing-room"
  },
  {
    "title": "Promising Retail Stocks Worth Watching \u2013 March 10th",
    "domain": "modernreaders.com",
    "seendate": "20250313",
    "url": "https://www.modernreaders.com/news/2025/03/13/promising-retail-stocks-worth-watching-march-10th.html"
  }
]